pythonpy_clone.py
pythonpy_clone-0.0.5.post1.dist-info/LICENSE.md
pythonpy_clone-0.0.5.post1.dist-info/METADATA
pythonpy_clone-0.0.5.post1.dist-info/WHEEL
pythonpy_clone-0.0.5.post1.dist-info/entry_points.txt
pythonpy_clone-0.0.5.post1.dist-info/top_level.txt
pythonpy_clone-0.0.5.post1.dist-info/RECORD
