Metadata-Version: 2.1
Name: pythonpy-clone
Version: 0.0.5.post1
Summary: rewrite of pythonpy using AST manipulations instead of regex
Home-page: https://github.com/ioistired/pythonpy-clone
Author: io mintz
License: BlueOak-1.0.0
Classifier: Development Status :: 3 - Alpha
Classifier: Environment :: Console
Classifier: Intended Audience :: Developers
Classifier: Intended Audience :: End Users/Desktop
Classifier: Intended Audience :: System Administrators
Classifier: Topic :: Utilities
Classifier: Natural Language :: English
Classifier: Operating System :: OS Independent
Requires-Python: >=3.6.0
License-File: LICENSE.md
Requires-Dist: import-expression <3.0.0,>=2.0.0
